Missing_Values_101703363/Missing_Values_101703363.py
Missing_Values_101703363/__init__.py
Missing_Values_101703363-0.9.dist-info/METADATA
Missing_Values_101703363-0.9.dist-info/WHEEL
Missing_Values_101703363-0.9.dist-info/entry_points.txt
Missing_Values_101703363-0.9.dist-info/top_level.txt
Missing_Values_101703363-0.9.dist-info/RECORD
